SiEPICLabTestParam/ElectroOpticDevice.py
SiEPICLabTestParam/TestParameters.py
SiEPICLabTestParam/__init__.py
SiEPICLabTestParam/__main__.py
SiEPICLabTestParam/autoMeasure.py
SiEPICLabTestParam/autoMeasurePanel.py
SiEPICLabTestParam/autoMeasureProgressDialog.py
SiEPICLabTestParam/cli.py
SiEPICLabTestParam/filterFrame.py
SiEPICLabTestParam/informationframes.py
SiEPICLabTestParam/logWriter.py
SiEPICLabTestParam/measurementRoutines.py
SiEPICLabTestParam/outputlogPanel.py
SiEPICLabTestParam3-0.0.16.dist-info/LICENSE
SiEPICLabTestParam3-0.0.16.dist-info/METADATA
SiEPICLabTestParam3-0.0.16.dist-info/WHEEL
SiEPICLabTestParam3-0.0.16.dist-info/top_level.txt
SiEPICLabTestParam3-0.0.16.dist-info/RECORD
